kickbase_bot/__init__.py
kickbase_bot/kickbase_bot.py
kickbase_bot/persistence.py
kickbase_bot/serialization.py
kickbase_bot/threading.py
Kickbase_Bot-0.0.15.dist-info/LICENSE
Kickbase_Bot-0.0.15.dist-info/METADATA
Kickbase_Bot-0.0.15.dist-info/WHEEL
Kickbase_Bot-0.0.15.dist-info/top_level.txt
Kickbase_Bot-0.0.15.dist-info/RECORD
