Metadata-Version: 2.1
Name: Kickbase-Bot
Version: 0.0.15
Summary: Python bot framework for kickbase
Home-page: https://github.com/kevinskyba/kickbase-bot
Author: kevinskyba
Author-email: kevinskyba@live.de
License: MIT
Platform: UNKNOWN
Requires-Dist: kickbase-api
Requires-Dist: pymongo
